vulnreach/__init__.py
vulnreach/cli.py
vulnreach/core.py
vulnreach/tracer_.py
vulnreach/utils/__init__.py
vulnreach/utils/exploitability_analyzer.py
vulnreach/utils/get_metadata.py
vulnreach/utils/java_reachability_analyzer.py
vulnreach/utils/multi_language_analyzer.py
vulnreach/utils/vuln_reachability_analyzer.py
vulnreach-1.0.1.dist-info/licenses/LICENSE
vulnreach-1.0.1.dist-info/METADATA
vulnreach-1.0.1.dist-info/WHEEL
vulnreach-1.0.1.dist-info/entry_points.txt
vulnreach-1.0.1.dist-info/top_level.txt
vulnreach-1.0.1.dist-info/RECORD
