Metadata-Version: 2.4
Name: vulnreach
Version: 1.0.1
Summary: Smart Vulnerability Reachability Analyzer - Beyond version checking
Author-email: Hrishikesh Nate <ihrishikeshnate@gmail.com>
Maintainer-email: Hrishikesh Nate <ihrishikeshnate@gmail.com>
License: MIT
Project-URL: Homepage, https://github.com/ihrishikesh0896/vulnreach
Project-URL: Documentation, https://github.com/ihrishikesh0896/vulnreach#readme
Project-URL: Repository, https://github.com/ihrishikesh0896/vulnreach.git
Project-URL: Bug Tracker, https://github.com/ihrishikesh0896/vulnreach/issues
Keywords: security,vulnerability,sca,sbom,reachability
Classifier: Development Status :: 4 - Beta
Classifier: Intended Audience :: Developers
Classifier: Intended Audience :: System Administrators
Classifier: License :: OSI Approved :: MIT License
Classifier: Operating System :: OS Independent
Classifier: Programming Language :: Python :: 3
Classifier: Programming Language :: Python :: 3.8
Classifier: Programming Language :: Python :: 3.9
Classifier: Programming Language :: Python :: 3.10
Classifier: Programming Language :: Python :: 3.11
Classifier: Programming Language :: Python :: 3.12
Classifier: Topic :: Security
Classifier: Topic :: Software Development :: Quality Assurance
Classifier: Topic :: System :: Systems Administration
Requires-Python: >=3.8
License-File: LICENSE
Requires-Dist: requests>=2.25.0
Requires-Dist: Flask
Requires-Dist: jinja2>=3.0.0
Requires-Dist: pandas>=1.3.0
Provides-Extra: dev
Requires-Dist: pytest>=6.0; extra == "dev"
Requires-Dist: pytest-cov>=2.0; extra == "dev"
Requires-Dist: black>=22.0; extra == "dev"
Requires-Dist: flake8>=4.0; extra == "dev"
Requires-Dist: mypy>=0.900; extra == "dev"
Provides-Extra: web
Requires-Dist: flask>=2.0.0; extra == "web"
Requires-Dist: gunicorn>=20.0.0; extra == "web"
Provides-Extra: export
Requires-Dist: jinja2>=3.0.0; extra == "export"
Dynamic: license-file
